home/__init__.py
home/action_decorators.py
home/app.py
home/device.py
home/device_generator.py
home/logger.py
home/storage.py
home/telegram_client.py
home/utils.py
smart_home-0.1.0.dist-info/METADATA
smart_home-0.1.0.dist-info/WHEEL
smart_home-0.1.0.dist-info/top_level.txt
smart_home-0.1.0.dist-info/RECORD
