Metadata-Version: 2.1
Name: smart-home
Version: 0.1.0
Summary: Smart Home Scenarios
Home-page: UNKNOWN
Author: Ivan Kriuchkov
Author-email: vivenchik@gmail.com
License: MIT
Platform: UNKNOWN
Classifier: Intended Audience :: Developers
Classifier: License :: OSI Approved :: MIT License
Classifier: Programming Language :: Python
Classifier: Programming Language :: Python :: 3
Classifier: Programming Language :: Python :: 3.11
Classifier: Operating System :: OS Independent
Requires-Dist: aiohttp[speedups]
Requires-Dist: aiofiles
Requires-Dist: pyyaml
Requires-Dist: python-telegram-bot[all,ext]
Requires-Dist: telegram
Requires-Dist: pydantic[dotenv]
Requires-Dist: async-lru
Requires-Dist: astral
